hadopy/__init__.py
hadopy/main.py
hadopy-0.1.8.dist-info/LICENSE
hadopy-0.1.8.dist-info/METADATA
hadopy-0.1.8.dist-info/WHEEL
hadopy-0.1.8.dist-info/entry_points.txt
hadopy-0.1.8.dist-info/top_level.txt
hadopy-0.1.8.dist-info/RECORD
