Metadata-Version: 2.1
Name: hadopy
Version: 0.1.8
Summary: Easy parallel map-reduce command line tool
Home-page: https://github.com/MariaDukmak/Hadopy
Author: Lucas van der Horst
Author-email: Lucas.vanderhorst@student.hu.nl
License: GPL3
Platform: UNKNOWN
Requires-Python: >=3.6
Requires-Dist: click (<8.0,>=7.0)
